BeginnersbookJspJiaochengChuyiFix1/README.md
BeginnersbookJspJiaochengChuyiFix1/__init__.py
BeginnersbookJspJiaochengChuyiFix1/__main__.py
BeginnersbookJspJiaochengChuyiFix1/file.epub
BeginnersbookJspJiaochengChuyiFix1/index.html
BeginnersbookJspJiaochengChuyiFix1/css/__init__.py
BeginnersbookJspJiaochengChuyiFix1/css/annotations.css
BeginnersbookJspJiaochengChuyiFix1/css/main.css
BeginnersbookJspJiaochengChuyiFix1/css/normalize.css
BeginnersbookJspJiaochengChuyiFix1/css/popup.css
BeginnersbookJspJiaochengChuyiFix1/font/__init__.py
BeginnersbookJspJiaochengChuyiFix1/font/fontello.eot
BeginnersbookJspJiaochengChuyiFix1/font/fontello.svg
BeginnersbookJspJiaochengChuyiFix1/font/fontello.ttf
BeginnersbookJspJiaochengChuyiFix1/font/fontello.woff
BeginnersbookJspJiaochengChuyiFix1/img/__init__.py
BeginnersbookJspJiaochengChuyiFix1/img/annotator-glyph-sprite.png
BeginnersbookJspJiaochengChuyiFix1/img/annotator-icon-sprite.png
BeginnersbookJspJiaochengChuyiFix1/img/apple-touch-icon.png
BeginnersbookJspJiaochengChuyiFix1/img/cancelfullscreen.png
BeginnersbookJspJiaochengChuyiFix1/img/close.png
BeginnersbookJspJiaochengChuyiFix1/img/fullscreen.png
BeginnersbookJspJiaochengChuyiFix1/img/loader.gif
BeginnersbookJspJiaochengChuyiFix1/img/menu-icon.png
BeginnersbookJspJiaochengChuyiFix1/img/save.png
BeginnersbookJspJiaochengChuyiFix1/img/saved.png
BeginnersbookJspJiaochengChuyiFix1/img/settings-s.png
BeginnersbookJspJiaochengChuyiFix1/img/settings.png
BeginnersbookJspJiaochengChuyiFix1/img/star.png
BeginnersbookJspJiaochengChuyiFix1/js/__init__.py
BeginnersbookJspJiaochengChuyiFix1/js/epub.js
BeginnersbookJspJiaochengChuyiFix1/js/epub.min.js
BeginnersbookJspJiaochengChuyiFix1/js/epub.min.map
BeginnersbookJspJiaochengChuyiFix1/js/hooks.min.js
BeginnersbookJspJiaochengChuyiFix1/js/hooks.min.map
BeginnersbookJspJiaochengChuyiFix1/js/reader.js
BeginnersbookJspJiaochengChuyiFix1/js/reader.js.map
BeginnersbookJspJiaochengChuyiFix1/js/reader.min.js
beginnersbook_jsp_jiaocheng_chuyi_fix1-2025.3.24.0.dist-info/METADATA
beginnersbook_jsp_jiaocheng_chuyi_fix1-2025.3.24.0.dist-info/WHEEL
beginnersbook_jsp_jiaocheng_chuyi_fix1-2025.3.24.0.dist-info/entry_points.txt
beginnersbook_jsp_jiaocheng_chuyi_fix1-2025.3.24.0.dist-info/top_level.txt
beginnersbook_jsp_jiaocheng_chuyi_fix1-2025.3.24.0.dist-info/RECORD
